Metadata-Version: 1.1
Name: pystpr
Version: 0.2
Summary: Easy to use Data Analysis functions for developers
Home-page: https://github.com/joaodlf/pystpr
Author: João Ferreira
Author-email: joao@joaodlf.com
License: UNKNOWN
Download-URL: https://github.com/joaodlf/pystpr/tarball/0.2
Keywords: statistics,probabilities
Platform: UNKNOWN
